kind/__init__.py
kind/__main__.py
kind/_kind.py
kind_wycliffwasonga-0.0.2.dist-info/LICENSE
kind_wycliffwasonga-0.0.2.dist-info/METADATA
kind_wycliffwasonga-0.0.2.dist-info/WHEEL
kind_wycliffwasonga-0.0.2.dist-info/entry_points.txt
kind_wycliffwasonga-0.0.2.dist-info/top_level.txt
kind_wycliffwasonga-0.0.2.dist-info/RECORD
